mission_control/__init__.py
mission_control/__main__.py
mission_control/agents/__init__.py
mission_control/agents/base.py
mission_control/agents/root_agent.py
mission_control/agents/specialized_agents.py
mission_control/cli.py
mission_control/core/__init__.py
mission_control/core/config.py
mission_control/core/orchestrator.py
mission_control/mcp.py
mission_control/memory/__init__.py
mission_control/memory/service.py
mission_control/terminal/__init__.py
mission_control/terminal/config_ui.py
mission_control/terminal/interface.py
mission_control/utils/__init__.py
mission_control/utils/monitoring.py
mission_control_ai-0.2.0.dist-info/LICENSE
mission_control_ai-0.2.0.dist-info/METADATA
mission_control_ai-0.2.0.dist-info/WHEEL
mission_control_ai-0.2.0.dist-info/RECORD
