Metadata-Version: 2.3
Name: mission-control-ai
Version: 0.2.0
Summary: AI Development Workflow Orchestration System
Keywords: ai,agents,development,orchestration,llm
Author: BlueArch
Author-email: contact@bluearch.io
Requires-Python: >=3.10,<4.0
Classifier: Development Status :: 4 - Beta
Classifier: Intended Audience :: Developers
Classifier: Programming Language :: Python :: 3
Classifier: Programming Language :: Python :: 3.10
Classifier: Programming Language :: Python :: 3.11
Classifier: Programming Language :: Python :: 3.12
Classifier: Programming Language :: Python :: 3.13
Classifier: Topic :: Scientific/Engineering :: Artificial Intelligence
Classifier: Topic :: Software Development :: Libraries :: Application Frameworks
Project-URL: Documentation, https://github.com/bluearchio/mission-control/wiki
Project-URL: Homepage, https://github.com/bluearchio/mission-control
Project-URL: Repository, https://github.com/bluearchio/mission-control
